Workbook

Sheet Startup Costs
A1: Treat Truck- Startup Costs
A2: Startup Item | B2: Category | C2: Cost | D2: Cost Type | E2: Source/Basis | F2: Annual/Recurring? | G2: Notes | I2: investment category | J2: cost
A3: Used food truck | B3: Vehicle | C3: 65000 | D3: planning estimate | E3: planning estimate | F3: NO | G3: Major startup investment; used truck | I3: Vehicle & branding | J3: 75000
A4: Customization & branding | B4: Vehicle/ Branding | C4: 10000 | D4: planning estimate | E4: planning estimate | F4: NO | G4: initial visual identify and truck mods | I4: Equipment | J4: 18500
A5: Equipment | B5: Equipment | C5: 18500 | D5: planning estimate | E5: planning estimate | F5: NO | G5: cooking & service equipment | I5: Inventory | J5: 5500
A6: Commissary deposit + first month | B6: Facility | C6: 2500 | D6: planning estimate | E6: planning estimate | F6: NO | G6: includes commissary deposit & 1st month | I6: Tech / Launch Marketing | J6: 4500
A7: Initial food inventory | B7: Inventory | C7: 4000 | D7: planning estimate | E7: planning estimate | F7: NO | G7: opening food invetory | I7: Facility/ Compliance | J7: 3050
A8: Initial packaging inventory | B8: Inventory | C8: 1500 | D8: planning estimate | E8: planning estimate | F8: NO | G8: opening packaing supply
A9: POS + Tech | B9: Technology | C9: 2000 | D9: planning estimate | E9: planning estimate | F9: NO | G9: initial POS hardare/softwqare setup
A10: Launch Marketing | B10: Marketing | C10: 2500 | D10: planning estimate | E10: planning estimate | F10: NO | G10: initial promo expenses
A11: GA LLC Formation | B11: Legal/compiance | C11: 110 | D11: research-based | E11: research-based | F11: NO | G11: GA business formation
A12: Douglasville Food Truck Permit | B12: Complaiance | C12: 100 | D12: research-based | E12: research-based | F12: NO | G12: douglasvilla mobile food truck permit
A13: Base of Ops Assessment | B13: Complaiance | C13: 95 | D13: research-based | E13: research-based | F13: NO | G13: base of pos assessment
A14: Businss Licence Fee | B14: Complaiance | C14: 50 | D14: research-based | E14: research-based | F14: NO | G14: business licnse/ occupational tax filing
A15: Health Inspection | B15: Complaiance | C15: 195 | D15: research-based | E15: research-based | F15: NO | G15: required health inspection
A16: Occupational Tax | B16: Complaiance | C16: 0 | D16: TBD | E16: TBD | F16: TBD | G16: amount to be confirmed
A17: Total Startup Costs | C17: =SUM(C3:C16) -> 106550

Sheet Menu & Product Costs
A1: Treat Truck- Menu & Product Costs
A2: Product | B2: Category | C2: Batch Yield | D2: Selling Price | E2: Direct cost/unit | F2: Gross profit/ unit | G2: Gross margin % | H2: Cost Type | I2: Source/Basis | J2: Notes
A3: Cheesecake Cup | B3: Core | C3: 24 | D3: 6 | E3: 1.89 | F3: =D3-E3 -> 4.11 | G3: =F3/D3 -> 0.685 | I3: restaurant depot | J3: 8-oz cup; crust or crustless; 24 batch
A4: Frozen Creation- 12 oz | B4: Core | C4: 5-gal batch | D4: 5 | E4: 0.77 | F4: =D4-E4 -> 4.23 | G4: =F4/D4 -> 0.846 | I4: restaurant depot | J4: frozen 12 oz: signature lemonade base + syrup
A5: Frozen Creation- 20 oz | B5: Core | C5: 5-gal batch | D5: 7 | E5: 1.49 | F5: =D5-E5 -> 5.51 | G5: =F5/D5 -> 0.78714286 | I5: restaurant depot | J5: frozen 20 oz: signature lemonade base + syrup
A6: Signature Cupcake | B6: Core | C6: 24 | D6: 5 | E6: 1.3 | F6: =D6-E6 -> 3.7 | G6: =F6/D6 -> 0.74 | I6: restaurant depot | J6: cupcake: vanilla bean base + frosting
A7: Individual Cobbler | B7: Core | C7: 16 | D7: 8 | E7: 2.8 | F7: =D7-E7 -> 5.2 | G7: =F7/D7 -> 0.65 | I7: restaurant depot | J7: cobbler 50/50 fruit-to-topping
A8: Cinnamon Roll | B8: Core | C8: 24 | D8: 6 | E8: 1.86 | F8: =D8-E8 -> 4.14 | G8: =F8/D8 -> 0.69 | I8: restaurant depot | J8: cinnamon roll: large bakery style
A9: Fudge | B9: Rotating | C9: 48 | D9: 4 | E9: 1.09 | F9: =D9-E9 -> 2.91 | G9: =F9/D9 -> 0.7275 | I9: restaurant depot | J9: fudge: choco/vanilla rotting flavors
A10: Pudding- Classic | B10: Rotating | C10: 24 | D10: 3.5 | E10: 0.74 | F10: =D10-E10 -> 2.76 | G10: =F10/D10 -> 0.78857143 | I10: restaurant depot | J10: pudding: 8 oz rotating signature flavors
A12: Average Selling Price | D12: =AVERAGE(D3:D10) -> 5.5625
A13: Average Direct Cost | D13: =AVERAGE(E3:E10) -> 1.4925
A14: Average Gross Margin | D14: =AVERAGE(G3:G10) -> 0.73927679

Sheet Sales Forecast
A1: Treat Truck - Annual Sales Forecast
A2: Month | B2: Service Days | C2: Customers/day | D2: Transactions | E2: Average Ticket Cost | F2: Gross Sales | G2: Food & Packaging % | H2: Food & Packaging cost | I2: Gross Profit | J2: Gross Margin % | K2: Source/Basis | L2: Notes
A3: January | B3: 18 | C3: 60 | D3: =B3*C3 -> 1080 | E3: 10 | F3: =D3*E3 -> 10800 | G3: 0.3 | H3: =F3*G3 -> 3240 | I3: =F3-H3 -> 7560 | J3: =I3/F3 -> 0.7 | K3: Business Planning Assump. | L3: 4 service days/week; 6 hours/day; 10 cust/hour
A4: February | B4: 16 | C4: 60 | D4: =B4*C4 -> 960 | E4: 10 | F4: =D4*E4 -> 9600 | G4: 0.3 | H4: =F4*G4 -> 2880 | I4: =F4-H4 -> 6720 | J4: =I4/F4 -> 0.7 | K4: Business Planning Assump.
A5: March | B5: 17 | C5: 60 | D5: =B5*C5 -> 1020 | E5: 10 | F5: =D5*E5 -> 10200 | G5: 0.3 | H5: =F5*G5 -> 3060 | I5: =F5-H5 -> 7140 | J5: =I5/F5 -> 0.7 | K5: Business Planning Assump.
A6: April | B6: 17 | C6: 60 | D6: =B6*C6 -> 1020 | E6: 10 | F6: =D6*E6 -> 10200 | G6: 0.3 | H6: =F6*G6 -> 3060 | I6: =F6-H6 -> 7140 | J6: =I6/F6 -> 0.7 | K6: Business Planning Assump.
A7: May | B7: 18 | C7: 60 | D7: =B7*C7 -> 1080 | E7: 10 | F7: =D7*E7 -> 10800 | G7: 0.3 | H7: =F7*G7 -> 3240 | I7: =F7-H7 -> 7560 | J7: =I7/F7 -> 0.7 | K7: Business Planning Assump.
A8: June | B8: 17 | C8: 60 | D8: =B8*C8 -> 1020 | E8: 10 | F8: =D8*E8 -> 10200 | G8: 0.3 | H8: =F8*G8 -> 3060 | I8: =F8-H8 -> 7140 | J8: =I8/F8 -> 0.7 | K8: Business Planning Assump.
A9: July | B9: 18 | C9: 60 | D9: =B9*C9 -> 1080 | E9: 10 | F9: =D9*E9 -> 10800 | G9: 0.3 | H9: =F9*G9 -> 3240 | I9: =F9-H9 -> 7560 | J9: =I9/F9 -> 0.7 | K9: Business Planning Assump.
A10: August | B10: 17 | C10: 60 | D10: =B10*C10 -> 1020 | E10: 10 | F10: =D10*E10 -> 10200 | G10: 0.3 | H10: =F10*G10 -> 3060 | I10: =F10-H10 -> 7140 | J10: =I10/F10 -> 0.7 | K10: Business Planning Assump.
A11: September | B11: 17 | C11: 60 | D11: =B11*C11 -> 1020 | E11: 10 | F11: =D11*E11 -> 10200 | G11: 0.3 | H11: =F11*G11 -> 3060 | I11: =F11-H11 -> 7140 | J11: =I11/F11 -> 0.7 | K11: Business Planning Assump.
A12: October | B12: 18 | C12: 60 | D12: =B12*C12 -> 1080 | E12: 10 | F12: =D12*E12 -> 10800 | G12: 0.3 | H12: =F12*G12 -> 3240 | I12: =F12-H12 -> 7560 | J12: =I12/F12 -> 0.7 | K12: Business Planning Assump.
A13: November | B13: 16 | C13: 60 | D13: =B13*C13 -> 960 | E13: 10 | F13: =D13*E13 -> 9600 | G13: 0.3 | H13: =F13*G13 -> 2880 | I13: =F13-H13 -> 6720 | J13: =I13/F13 -> 0.7 | K13: Business Planning Assump.
A14: December | B14: 19 | C14: 60 | D14: =B14*C14 -> 1140 | E14: 10 | F14: =D14*E14 -> 11400 | G14: 0.3 | H14: =F14*G14 -> 3420 | I14: =F14-H14 -> 7980 | J14: =I14/F14 -> 0.7 | K14: Business Planning Assump.
A16: Annual Financial Summary
A17: Annual Sales | F17: =SUM(F3:F14) -> 124800
A18: Average Monthtly sales | F18: =AVERAGE(F3:F14) -> 10400
A19: Highest Monthly Sales | F19: =MAX(F3:F14) -> 11400
A20: Annual Food & Packaging Cost | F20: =SUM(H3:H14) -> 37440
A21: Annual Gross Profit | F21: =SUM(I3:I14) -> 87360
A22: Lowest Monthly Sales | F22: =MIN(F3:F14) -> 9600
A23: Break-Even Status | F23: =IF(F17>='Break-Even'!B5,"Above Break-Even","Below Break-Even") -> Above Break-Even

Sheet Operating Expenses
A1: Treat Truck — Operating Expenses
A2: Expenses | B2: Category | C2: Monthly Cost | D2: Annual Cost | E2: Cost type | F2: Source/ Basis | G2: Notes
A3: Commissary | B3: facility | C3: 1000 | D3: =C3*12 -> 12000 | E3: planning estimate | F3: Nearby dedicated commissary benchmark | G3: Required base of operations
A4: Insurance | B4: insurance | C4: 300 | D4: =C4*12 -> 3600 | E4: planning estimate | F4: Food-truck insurance planning benchmark | G4: Truck/ business coverage
A5: Square Plus | B5: technology | C5: 49 | D5: =C5*12 -> 588 | E5: research-based | F5: Current Square Plus published pricing | G5: POS Software
A6: Mobile Business Data Phone | B6: technology | C6: 100 | D6: =C6*12 -> 1200 | E6: planning estimate | F6: Business planning estimate | G6: POS, phone, hotspot/data
A7: Fuel | B7: transportation | C7: 650 | D7: =C7*12 -> 7800 | E7: planning estimate | F7: 300 miles/week, 8 MPG, current GA gas price | G7: Mobile Operations and Travel
A8: Main & Repairs | B8: vehicle/equipement | C8: 400 | D8: =C8*12 -> 4800 | E8: planning estimate | F8: Used food truck maintenance reserve | G8: Truck and onboard equipment
A9: Cleaning & Sanitation | B9: operations | C9: 150 | D9: =C9*12 -> 1800 | E9: planning estimate | F9: Current foodservice supply pricing + planning allowance | G9: Truck and food-service sanitation
A10: Part-Time Labor | B10: labor | C10: 2392 | D10: =C10*12 -> 28704 | E10: planning estimate | F10: 30 hrs/week × $16/hr + payroll burden | G10: One part time serivce employee
A11: Payment Processing | B11: payment processing | C11: 416 | D11: =C11*12 -> 4992 | E11: calculated | F11: square Plus rate × projected transactions | G11: Varible with sales volume
A12: Marketing | B12: marketing | C12: 300 | D12: =C12*12 -> 3600 | E12: planning estimate | F12: Food-truck marketing benchmark + business planning assumption | G12: Ongoing Promotion
A14: Total Monthly Expenses | C14: =SUM(C3:C12) -> 5757
A15: Total Annual Expenses | C15: =SUM(D3:D12) -> 69084

Sheet Profit & Loss
A1: Treat Truck— Projected Profit & Loss
A2: Category | B2: Annual Amount
A3: Gross sales | B3: ='Sales Forecast'!F17 -> 124800
A4: Food & packaging | B4: ='Sales Forecast'!F20 -> 37440
A5: Gross profit | B5: =B3-B4 -> 87360
A6: Operating expenses | B6: ='Operating Expenses'!C15 -> 69084
A7: Operating profit | B7: =B5-B6 -> 18276

Sheet Break-Even
A1: Treat Truck- Break-Even Analysis
A2: Break-Even metric | B2: Amount
A3: Annual Operating expense | B3: ='Profit & Loss'!B6 -> 69084
A4: Contribution margin | B4: =1-'Sales Forecast'!G3 -> 0.7
A5: Annual-Break even sale | B5: =B3/B4 -> 98691.429
A6: Monthly Break Even sales | B6: =B5/12 -> 8224.2857
A7: Weekly Break Even sales | B7: =B5/52 -> 1897.9121
A8: Average Customer spend | B8: ='Sales Forecast'!E3 -> 10
A9: Break Even customer/week | B9: =B7/B8 -> 189.79121
A10: Break Even customer/day | B10: =B9/4 -> 47.447802

Sheet Revenue Chart

Sheet Expense-Profit Chart
A1: Category | B1: Annual Amount
A2: Operating expenses | B2: ='Profit & Loss'!B6 -> 69084
A3: Operating profit | B3: ='Profit & Loss'!B7 -> 18276
